strparsetools/__init__.py
strparsetools/parse.py
strparsetools-0.2.0.dist-info/LICENSE
strparsetools-0.2.0.dist-info/METADATA
strparsetools-0.2.0.dist-info/WHEEL
strparsetools-0.2.0.dist-info/top_level.txt
strparsetools-0.2.0.dist-info/RECORD
