Metadata-Version: 2.1
Name: strparsetools
Version: 0.2.0
Summary: A string parsing toolset
Home-page: https://github.com/siriusa51/strparsetools
Author: siriusa51
Author-email: siriusa51@outlook.com
License: MIT License
Platform: UNKNOWN
Classifier: Programming Language :: Python :: 3
Classifier: License :: OSI Approved :: MIT License
Classifier: Operating System :: OS Independent
Requires-Python: >=3
License-File: LICENSE
